odoo/addons/invader_invoice_payment/README.rst
odoo/addons/invader_invoice_payment/__init__.py
odoo/addons/invader_invoice_payment/__manifest__.py
odoo/addons/invader_invoice_payment/i18n/invader_invoice_payment.pot
odoo/addons/invader_invoice_payment/models/__init__.py
odoo/addons/invader_invoice_payment/models/account_move.py
odoo/addons/invader_invoice_payment/models/payment_transaction.py
odoo/addons/invader_invoice_payment/readme/CONTRIBUTORS.rst
odoo/addons/invader_invoice_payment/readme/DESCRIPTION.rst
odoo/addons/invader_invoice_payment/static/description/index.html
odoo/addons/invader_invoice_payment/views/account_move.xml
odoo14_addon_invader_invoice_payment-14.0.1.0.2.dist-info/METADATA
odoo14_addon_invader_invoice_payment-14.0.1.0.2.dist-info/WHEEL
odoo14_addon_invader_invoice_payment-14.0.1.0.2.dist-info/top_level.txt
odoo14_addon_invader_invoice_payment-14.0.1.0.2.dist-info/RECORD
